thegraph_gql_utils/__init__.py
thegraph_gql_utils/misc.py
thegraph_gql_utils/tools.py
thegraph_gql_utils/visitors.py
thegraph_gql_utils-1.2.0.dist-info/LICENSE
thegraph_gql_utils-1.2.0.dist-info/WHEEL
thegraph_gql_utils-1.2.0.dist-info/METADATA
thegraph_gql_utils-1.2.0.dist-info/RECORD
